{
  "party colours": {
    "999": [
      "#f7f7f7",
      "#cccccc",
      "#969696",
      "#636363",
      "#252525"
    ],
    "1": [
      "#eff3ff",
      "#bdd7e7",
      "#6baed6",
      "#3182bd",
      "#08519c"
    ],
    "16": [
      "#edf8e9",
      "#bae4b3",
      "#74c476",
      "#31a354",
      "#006d2c"
    ],
    "90": [
      "#feedde",
      "#fdbe85",
      "#fd8d3c",
      "#e6550d",
      "#a63603"
    ],
    "106": [
      "#feebe2",
      "#fbb4b9",
      "#f768a1",
      "#c51b8a",
      "#7a0177"
    ],
    "267": [
      "#ffffd4",
      "#fed98e",
      "#fe9929",
      "#d95f0e",
      "#993404"
    ],
    "303": [
      "#fee5d9",
      "#fcae91",
      "#fb6a4a",
      "#de2d26",
      "#a50f15"
    ],
    "350": [
      "#f6eff7",
      "#bdc9e1",
      "#67a9cf",
      "#1c9099",
      "#016c59"
    ]
  },
  "elections": {
    "presidential": {
      "2020": [
        "2020總統立委",
        "總統"
      ],
      "2016": [
        "2016總統立委",
        "總統"
      ],
      "2012": [
        "20120114-總統及立委",
        "總統"
      ],
      "2008": [
        "20080322-總統"
      ],
      "2004": [
        "2004   11任總統"
      ],
      "2000": [
        "2000年10任總統"
      ],
      "1996": [
        "9任總統"
      ]
    },
    "legislative": {
      "2020": [
        "2020總統立委",
        "不分區政黨"
      ],
      "2016": [
        "2016總統立委",
        "不分區政黨"
      ],
      "2012": [
        "20120114-總統及立委",
        "不分區政黨"
      ],
      "2008": [
        "2008立委",
        "不分區政黨"
      ]
    }
  }
}
